setup.py
lmk/__init__.py
lmk/__main__.py
lmk/api_client.py
lmk/cli.py
lmk/constants.py
lmk/exc.py
lmk/instance.py
lmk/methods.py
lmk/patches.py
lmk/shell_cli.py
lmk/shell_plugin.py
lmk/generated/__init__.py
lmk/generated/api_client.py
lmk/generated/configuration.py
lmk/generated/exceptions.py
lmk/generated/rest.py
lmk/generated/api/__init__.py
lmk/generated/api/app_api.py
lmk/generated/api/auth_api.py
lmk/generated/api/event_api.py
lmk/generated/api/headless_auth_api.py
lmk/generated/api/healthcheck_api.py
lmk/generated/api/notification_api.py
lmk/generated/api/oauth_api.py
lmk/generated/api/search_api.py
lmk/generated/api/session_api.py
lmk/generated/api/user_api.py
lmk/generated/models/__init__.py
lmk/generated/models/access_token_request.py
lmk/generated/models/access_token_response.py
lmk/generated/models/actor_response.py
lmk/generated/models/app_connection_response.py
lmk/generated/models/app_response.py
lmk/generated/models/create_app_request.py
lmk/generated/models/create_headless_auth_session_request.py
lmk/generated/models/create_notification_channel_request.py
lmk/generated/models/create_notification_channel_request_payload.py
lmk/generated/models/create_session_request.py
lmk/generated/models/create_session_request_state.py
lmk/generated/models/create_user_request.py
lmk/generated/models/create_user_response.py
lmk/generated/models/email_channel_payload.py
lmk/generated/models/event_notification_configuration.py
lmk/generated/models/event_request.py
lmk/generated/models/event_response.py
lmk/generated/models/event_search_result_response.py
lmk/generated/models/headless_auth_refresh_token_request.py
lmk/generated/models/headless_auth_session_response.py
lmk/generated/models/initiate_oauth_request.py
lmk/generated/models/initiate_oauth_response.py
lmk/generated/models/jupyter_session_state.py
lmk/generated/models/list_connected_apps_item_response.py
lmk/generated/models/list_connected_apps_response.py
lmk/generated/models/login_request.py
lmk_python-0.1.0.dist-info/METADATA
lmk_python-0.1.0.dist-info/WHEEL
lmk_python-0.1.0.dist-info/entry_points.txt
lmk_python-0.1.0.dist-info/licenses/LICENSE.txt
lmk_python-0.1.0.dist-info/RECORD
