Metadata-Version: 2.1
Name: lmk-python
Version: 0.1.0
Summary: Notifications you want, when you want them
Project-URL: Homepage, https://github.com/cfeenstra67/lmk-python
Author-email: Cam Feenstra <me@camfeenstra.com>
License: Copyright 2023 Cameron Feenstra
License-File: LICENSE.txt
Keywords: IPython,Jupyter,Widgets
Classifier: Framework :: Jupyter
Classifier: Intended Audience :: Developers
Classifier: Intended Audience :: Science/Research
Classifier: Programming Language :: Python
Classifier: Programming Language :: Python :: 3
Classifier: Programming Language :: Python :: 3.7
Classifier: Programming Language :: Python :: 3.8
Classifier: Programming Language :: Python :: 3.9
Classifier: Programming Language :: Python :: 3.10
Requires-Python: >=3.7
Requires-Dist: aiohttp<4
Requires-Dist: blinker<2
Requires-Dist: pydantic<2
Requires-Dist: python-dateutil<3
Requires-Dist: typing-extensions<5
Requires-Dist: urllib3<2
Provides-Extra: cli
Requires-Dist: click<9; extra == 'cli'
Provides-Extra: dev
Requires-Dist: black; extra == 'dev'
Requires-Dist: bump2version; extra == 'dev'
Requires-Dist: jupyterlab; extra == 'dev'
Provides-Extra: jupyter
Requires-Dist: ipython>=6.1.0; extra == 'jupyter'
Requires-Dist: ipywidgets>=7.0.0; extra == 'jupyter'
Provides-Extra: publish
Requires-Dist: build; extra == 'publish'
Requires-Dist: twine; extra == 'publish'
